[
  {
    "description": "English Premier League",
    "place": {
      "name": "Wembley Stadium",
      "image": "TODO"
    },
    "homeTeam": {
      "name": "Chelsea",
      "strength": "4",
      "image": "https://upload.wikimedia.org/wikipedia/pt/thumb/c/cc/Chelsea_FC.svg/800px-Chelsea_FC.svg.png"
    },
    "awayTeam": {
      "name": "Arsenal",
      "strength": "4",
      "image": "https://upload.wikimedia.org/wikipedia/pt/thumb/5/53/Arsenal_FC.svg/800px-Arsenal_FC.svg.png"
    }
  }  
] 
